odoo8_addon_l10n_br_purchase-8.0.1.0.0.99.dev14-py2.7-nspkg.pth
odoo_addons/l10n_br_purchase/__openerp__.py
odoo_addons/l10n_br_purchase/__init__.py
odoo_addons/l10n_br_purchase/README.rst
odoo_addons/l10n_br_purchase/security/l10n_br_purchase_security.xml
odoo_addons/l10n_br_purchase/security/ir.model.access.csv
odoo_addons/l10n_br_purchase/models/purchase.py
odoo_addons/l10n_br_purchase/models/__init__.py
odoo_addons/l10n_br_purchase/models/procurement.py
odoo_addons/l10n_br_purchase/models/res_company.py
odoo_addons/l10n_br_purchase/i18n/pt_BR.po
odoo_addons/l10n_br_purchase/test/purchase_order_demo.yml
odoo_addons/l10n_br_purchase/views/purchase_view.xml
odoo_addons/l10n_br_purchase/views/res_company_view.xml
odoo_addons/l10n_br_purchase/data/l10n_br_purchase_data.xml
odoo_addons/l10n_br_purchase/static/description/icon.png
odoo8_addon_l10n_br_purchase-8.0.1.0.0.99.dev14.dist-info/top_level.txt
odoo8_addon_l10n_br_purchase-8.0.1.0.0.99.dev14.dist-info/WHEEL
odoo8_addon_l10n_br_purchase-8.0.1.0.0.99.dev14.dist-info/RECORD
odoo8_addon_l10n_br_purchase-8.0.1.0.0.99.dev14.dist-info/metadata.json
odoo8_addon_l10n_br_purchase-8.0.1.0.0.99.dev14.dist-info/DESCRIPTION.rst
odoo8_addon_l10n_br_purchase-8.0.1.0.0.99.dev14.dist-info/METADATA
odoo8_addon_l10n_br_purchase-8.0.1.0.0.99.dev14.dist-info/namespace_packages.txt
