Metadata-Version: 2.0
Name: odoo8-addon-l10n-br-purchase
Version: 8.0.1.0.0.99.dev14
Summary: Brazilian Localization Purchase
Home-page: http://odoo-brasil.org
Author: Akretion, Odoo Community Association (OCA)
Author-email: support@odoo-community.org
License: AGPL-3
Platform: UNKNOWN
Requires-Dist: odoo (<9.0a,>=8.0a)
Requires-Dist: odoo8-addon-account-fiscal-position-rule-purchase
Requires-Dist: odoo8-addon-l10n-br-stock-account
Classifier: Programming Language :: Python :: 2.7
Classifier: Framework :: Odoo
Classifier: License :: OSI Approved :: GNU Affero General Public License v3
